blendercolors/__init__.py
blendercolors/bcolors.py
blendercolors-0.1.4.dist-info/licenses/LICENSE
blendercolors-0.1.4.dist-info/METADATA
blendercolors-0.1.4.dist-info/WHEEL
blendercolors-0.1.4.dist-info/top_level.txt
blendercolors-0.1.4.dist-info/RECORD
