Metadata-Version: 2.4
Name: blendercolors
Version: 0.1.4
Summary: The simplest module for color terminal output. Use ANSI sequences, working almost everywhere, no dependecies.
Author-email: TDH <tdhster@gmail.com>
License: GPL-3.0-or-later
Project-URL: Homepage, https://github.com/tdhster/blendercolors
Keywords: ansi,terminal,colors,easy,gpl,class
Classifier: License :: OSI Approved :: GNU General Public License v3 or later (GPLv3+)
Classifier: Programming Language :: Python :: 3
Classifier: Operating System :: OS Independent
Requires-Python: >=3.7
License-File: LICENSE
Dynamic: license-file
